hijiki/__init__.py
hijiki/logger.py
hijiki/adapters/__init__.py
hijiki/adapters/rabbitmq_adapter.py
hijiki/adapters/rabbitmq_broker.py
hijiki/adapters/rabbitmq_consumer_adapter.py
hijiki/adapters/rabbitmq_publisher_adapter.py
hijiki/builders/__init__.py
hijiki/builders/message_builder.py
hijiki/config/__init__.py
hijiki/config/broker_config.py
hijiki/config/broker_env_vars.py
hijiki/config/broker_type.py
hijiki/config/consumer_data.py
hijiki/connection/__init__.py
hijiki/connection/rabbitmq_connection.py
hijiki/decorators/__init__.py
hijiki/decorators/decorator.py
hijiki/manager/__init__.py
hijiki/manager/message_manager.py
hijiki/manager/message_manager_builder.py
hijiki/models/__init__.py
hijiki/models/message_cover.py
hijiki/ports/__init__.py
hijiki/ports/message_broker.py
hijiki-2.0.85.dist-info/licenses/LICENSE
hijiki-2.0.85.dist-info/METADATA
hijiki-2.0.85.dist-info/WHEEL
hijiki-2.0.85.dist-info/top_level.txt
hijiki-2.0.85.dist-info/RECORD
