Metadata-Version: 2.4
Name: hijiki
Version: 2.0.85
Summary: Python Rabbit wrapper library to simplify to use Exchanges and Queues with decorators
Author: Leandro Vilson Battisti
Keywords: RabbitMQ,decorator
License-File: LICENSE
Dynamic: author
Dynamic: description
Dynamic: description-content-type
Dynamic: keywords
Dynamic: license-file
Dynamic: summary
